<?xml version="1.0" encoding="utf-8"?>
<!DOCTYPE hibernate-mapping PUBLIC "-//Hibernate/Hibernate Mapping DTD 3.0//EN"
"http://hibernate.sourceforge.net/hibernate-mapping-3.0.dtd">
<!-- 
    Mapping file autogenerated by MyEclipse Persistence Tools
-->
<hibernate-mapping package="com.mp100.risk.ap.team.domain.hibernate.dv">
    <class name="MembersPictureView" table="x_ap_members_picture">
        <comment>成员管理表</comment>
        <id name="pictureId" type="java.lang.String">
            <column name="PICTURE_ID" length="32">
            	<comment>头像标识</comment>
            </column>
            <generator class="uuid.hex"></generator>
        </id>
        <property name="membersId" type="java.lang.String">
            <column name="MEMBERS_ID" length="32">
                <comment>成员标识</comment>
            </column>
        </property>
        <property name="pictureName" type="java.sql.Blob">
            <column name="PICTURE_NAME">
                <comment>头像名称</comment>
            </column>
        </property>
    </class>
    
     <sql-query name="com.mp100.risk.ap.team.domain.hibernate.dv.queryMembersPictureViewDV">
       <return alias="MembersPictureView" class="com.mp100.risk.ap.team.domain.hibernate.dv.MembersPictureView"></return>
     <![CDATA[
			 select 
			 		p.PICTURE_ID,
			 		p.MEMBERS_ID,
			 		p.PICTURE_NAME
			 from		
			 		X_AP_MEMBERS_PICTURE p, X_AP_MEMBERS m
			 where  
			 		p.MEMBERS_ID = m.MEMBERS_ID
			 		and (p.MEMBERS_ID = :QT_membersId)
      ]]>
    </sql-query>
    
</hibernate-mapping>
